gemo/__init__.py
gemo/_version.py
gemo/camera.py
gemo/gemo.py
gemo/geometries.py
gemo/utils.py
gemo/backends/__init__.py
gemo/backends/matplotlib.py
gemo/backends/plotly.py
gemo-0.1.2.dist-info/LICENSE
gemo-0.1.2.dist-info/METADATA
gemo-0.1.2.dist-info/WHEEL
gemo-0.1.2.dist-info/top_level.txt
gemo-0.1.2.dist-info/RECORD
